{
    "author": {
        "name": "William Gibson",
        "birth_date": "1948-03-17",
        "nationality": "Canadian-American",
        "bibliography": [
            {
                "name": "Neuromancer",
                "year": 1984,
                "type": "Novel"
            },
            {
                "name": "Count Zero",
                "year": 1986,
                "type": "Novel"
            },
            {
                "name": "Mona Lisa Overdrive",
                "year": 1988,
                "type": "Novel"
            },
            {
                "name": "Virtual Light",
                "year": 1993,
                "type": "Novel"
            },
            {
                "name": "Idoru",
                "year": 1996,
                "type": "Novel"
            },
            {
                "name": "All Tomorrow's Parties",
                "year": 1999,
                "type": "Novel"
            },
            {
                "name": "Pattern Recognition",
                "year": 2003,
                "type": "Novel"
            },
            {
                "name": "Spook Country",
                "year": 2007,
                "type": "Novel"
            },
            {
                "name": "Zero History",
                "year": 2010,
                "type": "Novel"
            },
            {
                "name": "The Peripheral",
                "year": 2014,
                "type": "Novel"
            },
            {
                "name": "Agency",
                "year": 2020,
                "type": "Novel"
            },
            {
                "name": "Burning Chrome",
                "year": 1986,
                "type": "Collection"
            }
        ]
    }
}
